trakit/__init__.py
trakit/__main__.py
trakit/api.py
trakit/config.py
trakit/context.py
trakit/converters/__init__.py
trakit/converters/country.py
trakit/converters/language.py
trakit/data/config.json
trakit/language.py
trakit/patterns.py
trakit/words.py
trakit-0.2.4.dist-info/LICENSE
trakit-0.2.4.dist-info/METADATA
trakit-0.2.4.dist-info/WHEEL
trakit-0.2.4.dist-info/entry_points.txt
trakit-0.2.4.dist-info/RECORD
